ngql/__init__.py
ngql/magic.py
ngql/ng_load.py
ngql/types.py
ngql/utils.py
jupyter_nebulagraph-0.14.3.dist-info/LICENSE
jupyter_nebulagraph-0.14.3.dist-info/METADATA
jupyter_nebulagraph-0.14.3.dist-info/WHEEL
jupyter_nebulagraph-0.14.3.dist-info/top_level.txt
jupyter_nebulagraph-0.14.3.dist-info/RECORD
