Metadata-Version: 2.1
Name: jupyter_nebulagraph
Version: 0.14.3
Summary: Jupyter extension for NebulaGraph
Home-page: https://github.com/wey-gu/jupyter_nebulagraph
Author: Wey Gu
Author-email: weyl.gu@gmail.com
Project-URL: Bug Tracker, https://github.com/wey-gu/jupyter_nebulagraph/issues
Project-URL: Documentation, https://jupyter-nebulagraph.readthedocs.io/
Classifier: Programming Language :: Python :: 3
Classifier: License :: OSI Approved :: Apache Software License
Classifier: Operating System :: OS Independent
Requires-Python: >=3.6
License-File: LICENSE
Requires-Dist: Jinja2
Requires-Dist: nebula3-python >=3.8.0
Requires-Dist: pandas
Requires-Dist: tqdm
Requires-Dist: pyvis
Requires-Dist: requests
Requires-Dist: pydantic
Requires-Dist: scipy
Requires-Dist: ipywidgets
Requires-Dist: pyarrow
